libwon/__init__.py
libwon/utils/__init__.py
libwon/utils/cloud.py
libwon/utils/collector.py
libwon/utils/misc.py
libwon/utils/mp.py
libwon/utils/para.py
libwon-0.0.2.dist-info/METADATA
libwon-0.0.2.dist-info/WHEEL
libwon-0.0.2.dist-info/top_level.txt
libwon-0.0.2.dist-info/RECORD
