Metadata-Version: 2.1
Name: libwon
Version: 0.0.2
Summary: A simple lib to automatically manage the parallelled experiments
Home-page: https://github.com/wondergo2017/libwon/tree/main
Author: wondergo
Author-email: wondergo2017@gmail.com
License: UNKNOWN
Platform: UNKNOWN
Requires-Python: >=3.6
Requires-Dist: matplotlib
Requires-Dist: pandas
Requires-Dist: requests
